{"data":[{"codparticipant":40664926,"jugador":"IVO","dorsal":8,"any":2010,"codequip":41270773,"nom_equip":"BARCELONETA, C.F. B","escut":"00100_0000173440_LOGO_FCB.png","minut":1,"jornada":1,"tipus":"normal"},{"codparticipant":49046880,"jugador":"AMIN","dorsal":7,"any":2011,"codequip":41270773,"nom_equip":"BARCELONETA, C.F. B","escut":"00100_0000173440_LOGO_FCB.png","minut":8,"jornada":1,"tipus":"normal"},{"codparticipant":33525193,"jugador":"TOMAS","dorsal":10,"any":2010,"codequip":41270773,"nom_equip":"BARCELONETA, C.F. B","escut":"00100_0000173440_LOGO_FCB.png","minut":18,"jornada":1,"tipus":"normal"},{"codparticipant":33525193,"jugador":"TOMAS","dorsal":10,"any":2010,"codequip":41270773,"nom_equip":"BARCELONETA, C.F. B","escut":"00100_0000173440_LOGO_FCB.png","minut":25,"jornada":1,"tipus":"normal"},{"codparticipant":33525193,"jugador":"TOMAS","dorsal":10,"any":2010,"codequip":41270773,"nom_equip":"BARCELONETA, C.F. B","escut":"00100_0000173440_LOGO_FCB.png","minut":30,"jornada":1,"tipus":"normal"},{"codparticipant":49055406,"jugador":"SIDI UNAI","dorsal":6,"any":2011,"codequip":41270773,"nom_equip":"BARCELONETA, C.F. B","escut":"00100_0000173440_LOGO_FCB.png","minut":33,"jornada":1,"tipus":"normal"},{"codparticipant":40664926,"jugador":"IVO","dorsal":8,"any":2010,"codequip":41270773,"nom_equip":"BARCELONETA, C.F. B","escut":"00100_0000173440_LOGO_FCB.png","minut":39,"jornada":1,"tipus":"normal"},{"codparticipant":49055406,"jugador":"SIDI UNAI","dorsal":6,"any":2011,"codequip":41270773,"nom_equip":"BARCELONETA, C.F. B","escut":"00100_0000173440_LOGO_FCB.png","minut":41,"jornada":1,"tipus":"normal"},{"codparticipant":49055406,"jugador":"SIDI UNAI","dorsal":6,"any":2011,"codequip":41270773,"nom_equip":"BARCELONETA, C.F. B","escut":"00100_0000173440_LOGO_FCB.png","minut":46,"jornada":1,"tipus":"normal"},{"codparticipant":33731894,"jugador":"HAITAM","dorsal":3,"any":2010,"codequip":41270773,"nom_equip":"BARCELONETA, C.F. B","escut":"00100_0000173440_LOGO_FCB.png","minut":50,"jornada":1,"tipus":"normal"},{"codparticipant":49045875,"jugador":"CRISTOPHER","dorsal":5,"any":2010,"codequip":41270773,"nom_equip":"BARCELONETA, C.F. B","escut":"00100_0000173440_LOGO_FCB.png","minut":51,"jornada":1,"tipus":"normal"},{"codparticipant":41825121,"jugador":"SERGI MIQUEL","dorsal":9,"any":2010,"codequip":41270773,"nom_equip":"BARCELONETA, C.F. B","escut":"00100_0000173440_LOGO_FCB.png","minut":55,"jornada":1,"tipus":"normal"},{"codparticipant":41825121,"jugador":"SERGI MIQUEL","dorsal":9,"any":2010,"codequip":41270773,"nom_equip":"BARCELONETA, C.F. B","escut":"00100_0000173440_LOGO_FCB.png","minut":56,"jornada":1,"tipus":"normal"},{"codparticipant":33525193,"jugador":"TOMAS","dorsal":10,"any":2010,"codequip":41270773,"nom_equip":"BARCELONETA, C.F. B","escut":"00100_0000173440_LOGO_FCB.png","minut":68,"jornada":1,"tipus":"normal"},{"codparticipant":49432510,"jugador":"MOHAMED KHAYRDIN","dorsal":15,"any":2010,"codequip":41270773,"nom_equip":"BARCELONETA, C.F. B","escut":"00100_0000173440_LOGO_FCB.png","minut":66,"jornada":3,"tipus":"normal"},{"codparticipant":49046880,"jugador":"AMIN","dorsal":7,"any":2011,"codequip":41270773,"nom_equip":"BARCELONETA, C.F. B","escut":"00100_0000173440_LOGO_FCB.png","minut":12,"jornada":4,"tipus":"normal"},{"codparticipant":41825618,"jugador":"BRYAN","dorsal":20,"any":2011,"codequip":41270773,"nom_equip":"BARCELONETA, C.F. B","escut":"00100_0000173440_LOGO_FCB.png","minut":9,"jornada":5,"tipus":"normal"},{"codparticipant":49432510,"jugador":"MOHAMED KHAYRDIN","dorsal":16,"any":2010,"codequip":41270773,"nom_equip":"BARCELONETA, C.F. B","escut":"00100_0000173440_LOGO_FCB.png","minut":50,"jornada":7,"tipus":"normal"},{"codparticipant":49432510,"jugador":"MOHAMED KHAYRDIN","dorsal":16,"any":2010,"codequip":41270773,"nom_equip":"BARCELONETA, C.F. B","escut":"00100_0000173440_LOGO_FCB.png","minut":60,"jornada":7,"tipus":"normal"},{"codparticipant":49432510,"jugador":"MOHAMED KHAYRDIN","dorsal":16,"any":2010,"codequip":41270773,"nom_equip":"BARCELONETA, C.F. B","escut":"00100_0000173440_LOGO_FCB.png","minut":69,"jornada":7,"tipus":"normal"},{"codparticipant":49046526,"jugador":"AKTER","dorsal":14,"any":2011,"codequip":41270773,"nom_equip":"BARCELONETA, C.F. B","escut":"00100_0000173440_LOGO_FCB.png","minut":30,"jornada":8,"tipus":"normal"},{"codparticipant":49047214,"jugador":"SAMEER ALI","dorsal":12,"any":2010,"codequip":41270773,"nom_equip":"BARCELONETA, C.F. B","escut":"00100_0000173440_LOGO_FCB.png","minut":3,"jornada":9,"tipus":"normal"},{"codparticipant":41825618,"jugador":"BRYAN","dorsal":18,"any":2011,"codequip":41270773,"nom_equip":"BARCELONETA, C.F. B","escut":"00100_0000173440_LOGO_FCB.png","minut":6,"jornada":9,"tipus":"normal"},{"codparticipant":49046880,"jugador":"AMIN","dorsal":7,"any":2011,"codequip":41270773,"nom_equip":"BARCELONETA, C.F. B","escut":"00100_0000173440_LOGO_FCB.png","minut":17,"jornada":9,"tipus":"normal"},{"codparticipant":49432510,"jugador":"MOHAMED KHAYRDIN","dorsal":18,"any":2010,"codequip":41270773,"nom_equip":"BARCELONETA, C.F. B","escut":"00100_0000173440_LOGO_FCB.png","minut":12,"jornada":11,"tipus":"normal"},{"codparticipant":49046526,"jugador":"AKTER","dorsal":23,"any":2011,"codequip":41270773,"nom_equip":"BARCELONETA, C.F. B","escut":"00100_0000173440_LOGO_FCB.png","minut":14,"jornada":11,"tipus":"normal"},{"codparticipant":49055406,"jugador":"SIDI UNAI","dorsal":6,"any":2011,"codequip":41270773,"nom_equip":"BARCELONETA, C.F. B","escut":"00100_0000173440_LOGO_FCB.png","minut":37,"jornada":11,"tipus":"normal"},{"codparticipant":49042711,"jugador":"QIHAO","dorsal":8,"any":2010,"codequip":41270773,"nom_equip":"BARCELONETA, C.F. B","escut":"00100_0000173440_LOGO_FCB.png","minut":49,"jornada":11,"tipus":"normal"},{"codparticipant":49042711,"jugador":"QIHAO","dorsal":9,"any":2010,"codequip":41270773,"nom_equip":"BARCELONETA, C.F. B","escut":"00100_0000173440_LOGO_FCB.png","minut":8,"jornada":12,"tipus":"normal"},{"codparticipant":49046621,"jugador":"HECTOR","dorsal":1,"any":2010,"codequip":41270773,"nom_equip":"BARCELONETA, C.F. B","escut":"00100_0000173440_LOGO_FCB.png","minut":59,"jornada":13,"tipus":"propia"},{"codparticipant":49185370,"jugador":"KILIAN","dorsal":14,"any":2010,"codequip":41270773,"nom_equip":"BARCELONETA, C.F. B","escut":"00100_0000173440_LOGO_FCB.png","minut":25,"jornada":14,"tipus":"penalti"},{"codparticipant":49047214,"jugador":"SAMEER ALI","dorsal":12,"any":2010,"codequip":41270773,"nom_equip":"BARCELONETA, C.F. B","escut":"00100_0000173440_LOGO_FCB.png","minut":28,"jornada":14,"tipus":"normal"},{"codparticipant":49042711,"jugador":"QIHAO","dorsal":8,"any":2010,"codequip":41270773,"nom_equip":"BARCELONETA, C.F. B","escut":"00100_0000173440_LOGO_FCB.png","minut":43,"jornada":14,"tipus":"normal"},{"codparticipant":49055406,"jugador":"SIDI UNAI","dorsal":6,"any":2011,"codequip":41270773,"nom_equip":"BARCELONETA, C.F. B","escut":"00100_0000173440_LOGO_FCB.png","minut":47,"jornada":14,"tipus":"normal"},{"codparticipant":49046526,"jugador":"AKTER","dorsal":19,"any":2011,"codequip":41270773,"nom_equip":"BARCELONETA, C.F. B","escut":"00100_0000173440_LOGO_FCB.png","minut":49,"jornada":14,"tipus":"normal"},{"codparticipant":49046880,"jugador":"AMIN","dorsal":7,"any":2011,"codequip":41270773,"nom_equip":"BARCELONETA, C.F. B","escut":"00100_0000173440_LOGO_FCB.png","minut":59,"jornada":14,"tipus":"normal"},{"codparticipant":33153134,"jugador":"YASER","dorsal":4,"any":2010,"codequip":41270773,"nom_equip":"BARCELONETA, C.F. B","escut":"00100_0000173440_LOGO_FCB.png","minut":47,"jornada":15,"tipus":"propia"},{"codparticipant":49432510,"jugador":"MOHAMED KHAYRDIN","dorsal":18,"any":2010,"codequip":41270773,"nom_equip":"BARCELONETA, C.F. B","escut":"00100_0000173440_LOGO_FCB.png","minut":58,"jornada":16,"tipus":"normal"},{"codparticipant":49042711,"jugador":"QIHAO","dorsal":8,"any":2010,"codequip":41270773,"nom_equip":"BARCELONETA, C.F. B","escut":"00100_0000173440_LOGO_FCB.png","minut":65,"jornada":18,"tipus":"normal"},{"codparticipant":33731894,"jugador":"HAITAM","dorsal":3,"any":2010,"codequip":41270773,"nom_equip":"BARCELONETA, C.F. B","escut":"00100_0000173440_LOGO_FCB.png","minut":16,"jornada":20,"tipus":"normal"},{"codparticipant":49042711,"jugador":"QIHAO","dorsal":8,"any":2010,"codequip":41270773,"nom_equip":"BARCELONETA, C.F. B","escut":"00100_0000173440_LOGO_FCB.png","minut":22,"jornada":20,"tipus":"normal"},{"codparticipant":49042711,"jugador":"QIHAO","dorsal":8,"any":2010,"codequip":41270773,"nom_equip":"BARCELONETA, C.F. B","escut":"00100_0000173440_LOGO_FCB.png","minut":63,"jornada":20,"tipus":"normal"},{"codparticipant":49047214,"jugador":"SAMEER ALI","dorsal":12,"any":2010,"codequip":41270773,"nom_equip":"BARCELONETA, C.F. B","escut":"00100_0000173440_LOGO_FCB.png","minut":69,"jornada":20,"tipus":"normal"}],"codequip":"41270773","codgroup":"48438234","menuFollowTeams":[{"label":"Inf A","href":"/classificacio?id=48067560"},{"label":"Inf B","href":"/classificacio?id=48067652"},{"label":"Inf C","href":"/classificacio?id=48438234"},{"label":"Inf D","href":"/classificacio?id=48438025"}]}