{"data":{"INFO":{"CODGRUPO":"48067652","GOLES_CASA":"0","GOLES_FUERA":"7","PENALTIS_CASA":null,"PENALTIS_FUERA":null,"CODACTA":"3261945","COD_COMPETICION":47108843,"NOM_COMPETICION":"INFANTIL PRIMERA DIVISIÓ","NOM_COMPETICION_URL":"infantil-primera-divisio","COD_GRUPO":48067652,"GRUPO":"GRUP 3","GRUPO_URL":"grup-3","CODEQUIPO_CASA":"18482665","CODEQUIPO_FUERA":"38099","JORNADA":"13","CODIGO_CAMPO":"756","COMIENZO1":"2024-01-13 15:00:00","SUSPENDIDO":"0","NOMBRE":"ESTADI MPAL. NOU DE SANTA COLOMA DE GRAMENET CAN PEIXAUET","DIRECCION":"av. de Can Peixauet, s/n","TEMP_NOMBRE":"2324","TEMP_LARGO":"TEMPORADA 2023-2024","CIUDAD":"Santa Coloma de Gramenet","ESTADO":"4"},"ARBITROS":[{"CODTIPO_ARBITRO":"1","CODARBITRO":"8761","NOMBRE_ARBITRO":"GERARD","NOMBRE":"Barcelona1"}],"GOLES":[{"NOMBRE":"GERARD","LICENCIA":"17","DORSAL":"6","CODPARTICIPANTE":"30169013","FECHA_NACIMIENTO":1,"PORTERO":null,"TIPO":"normal","MINUTO":"38","EQUIPO":"visitante"},{"NOMBRE":"ADRIAN","LICENCIA":"17","DORSAL":"7","CODPARTICIPANTE":"35934261","FECHA_NACIMIENTO":1,"PORTERO":null,"TIPO":"normal","MINUTO":"65","EQUIPO":"visitante"},{"NOMBRE":"EDUARD","LICENCIA":"17","DORSAL":"10","CODPARTICIPANTE":"28651862","FECHA_NACIMIENTO":1,"PORTERO":null,"TIPO":"normal","MINUTO":"55","EQUIPO":"visitante"},{"NOMBRE":"EDUARD","LICENCIA":"17","DORSAL":"10","CODPARTICIPANTE":"28651862","FECHA_NACIMIENTO":1,"PORTERO":null,"TIPO":"normal","MINUTO":"60","EQUIPO":"visitante"},{"NOMBRE":"HUGO","LICENCIA":"17","DORSAL":"26","CODPARTICIPANTE":"39290299","FECHA_NACIMIENTO":2,"PORTERO":null,"TIPO":"normal","MINUTO":"6","EQUIPO":"visitante"},{"NOMBRE":"ANDERSON-IVAN","LICENCIA":"17","DORSAL":"34","CODPARTICIPANTE":"25802309","FECHA_NACIMIENTO":2,"PORTERO":null,"TIPO":"normal","MINUTO":"13","EQUIPO":"visitante"},{"NOMBRE":"ANDERSON-IVAN","LICENCIA":"17","DORSAL":"34","CODPARTICIPANTE":"25802309","FECHA_NACIMIENTO":2,"PORTERO":null,"TIPO":"normal","MINUTO":"62","EQUIPO":"visitante"}],"EQUIPO_CASA":{"CODCLUB":6467,"CODCLUB2":18476477,"CODEQUIPO":18482665,"NOMBRE_CLUB":"FUNDACIÓ ESPORTIVA GRAMA","NOMBRE_CLUB_URL":"fundacio-esportiva-grama","NOMBRE_EQUIPO":"FUNDACIÓ ESPORTIVA GRAMA B","NOMBRE_EQUIPO_URL":"fundacio-esportiva-grama-b","NOMBRE":"00100_0000574709_fgrama_200x200.png","NOMBRE_ABREVIADO_URL":"1i","CODGRUPO":44760491,"TITULARES":[{"NOMBRE":"HUGO","LICENCIA":"17","DORSAL":"4","CODPARTICIPANTE":"30529835","FECHA_NACIMIENTO":1,"PORTERO":null},{"NOMBRE":"ERIK","LICENCIA":"17","DORSAL":"5","CODPARTICIPANTE":"28821553","FECHA_NACIMIENTO":2,"PORTERO":null},{"NOMBRE":"ALAN","LICENCIA":"17","DORSAL":"6","CODPARTICIPANTE":"29681470","FECHA_NACIMIENTO":1,"PORTERO":null},{"NOMBRE":"EDGAR","LICENCIA":"17","DORSAL":"7","CODPARTICIPANTE":"35482879","FECHA_NACIMIENTO":1,"PORTERO":null},{"NOMBRE":"CRISTIAN","LICENCIA":"17","DORSAL":"8","CODPARTICIPANTE":"33115773","FECHA_NACIMIENTO":2,"PORTERO":null},{"NOMBRE":"GERARD","LICENCIA":"17","DORSAL":"9","CODPARTICIPANTE":"35349740","FECHA_NACIMIENTO":1,"PORTERO":null},{"NOMBRE":"ALEIX","LICENCIA":"17","DORSAL":"11","CODPARTICIPANTE":"33306659","FECHA_NACIMIENTO":1,"PORTERO":null},{"NOMBRE":"ALEX","LICENCIA":"17","DORSAL":"12","CODPARTICIPANTE":"33656550","FECHA_NACIMIENTO":2,"PORTERO":null},{"NOMBRE":"SERGI","LICENCIA":"17","DORSAL":"13","CODPARTICIPANTE":"28694367","FECHA_NACIMIENTO":1,"PORTERO":1},{"NOMBRE":"BIEL","LICENCIA":"17","DORSAL":"15","CODPARTICIPANTE":"28505336","FECHA_NACIMIENTO":1,"PORTERO":null},{"NOMBRE":"POL","LICENCIA":"17","DORSAL":"17","CODPARTICIPANTE":"28950517","FECHA_NACIMIENTO":1,"PORTERO":null}],"SUPLENTES":[{"NOMBRE":"TONY","LICENCIA":"17","DORSAL":"1","CODPARTICIPANTE":"29609313","FECHA_NACIMIENTO":1,"PORTERO":1},{"NOMBRE":"EDGAR","LICENCIA":"17","DORSAL":"10","CODPARTICIPANTE":"25851122","FECHA_NACIMIENTO":2,"PORTERO":null},{"NOMBRE":"ERICK KAUAN","LICENCIA":"17","DORSAL":"14","CODPARTICIPANTE":"30992074","FECHA_NACIMIENTO":1,"PORTERO":null},{"NOMBRE":"ALEX","LICENCIA":"17","DORSAL":"19","CODPARTICIPANTE":"42176937","FECHA_NACIMIENTO":1,"PORTERO":null},{"NOMBRE":"ERIC","LICENCIA":"17","DORSAL":"20","CODPARTICIPANTE":"27067769","FECHA_NACIMIENTO":1,"PORTERO":null}],"COSTECNIC":{"Entrenador Titular":"ALBERTO","Delegat":"RUBEN"},"SUSTITUCIONES":[],"SANCIONES":[{"NOMBRE":"HUGO","LICENCIA":"17","DORSAL":"4","CODPARTICIPANTE":"30529835","FECHA_NACIMIENTO":1,"PORTERO":null,"TIPO":"groga","MINUTO":"44"}]},"EQUIPO_FUERA":{"CODCLUB":1032,"CODCLUB2":1032,"CODEQUIPO":38099,"NOMBRE_CLUB":"MARTINENC, F.C.","NOMBRE_CLUB_URL":"martinenc-fc","NOMBRE_EQUIPO":"MARTINENC, F.C. B","NOMBRE_EQUIPO_URL":"martinenc-fc-b","NOMBRE":"00100_0000577607_martinenc-200x200.png","NOMBRE_ABREVIADO_URL":"1i","CODGRUPO":44760295,"TITULARES":[{"NOMBRE":"ADRIÀ","LICENCIA":"17","DORSAL":"1","CODPARTICIPANTE":"26826506","FECHA_NACIMIENTO":2,"PORTERO":1},{"NOMBRE":"EDUARD","LICENCIA":"17","DORSAL":"10","CODPARTICIPANTE":"28651862","FECHA_NACIMIENTO":1,"PORTERO":null},{"NOMBRE":"GUIFRÉ","LICENCIA":"17","DORSAL":"16","CODPARTICIPANTE":"30169138","FECHA_NACIMIENTO":1,"PORTERO":null},{"NOMBRE":"ARNAU","LICENCIA":"17","DORSAL":"20","CODPARTICIPANTE":"35030014","FECHA_NACIMIENTO":2,"PORTERO":null},{"NOMBRE":"AITOR","LICENCIA":"17","DORSAL":"23","CODPARTICIPANTE":"35212498","FECHA_NACIMIENTO":1,"PORTERO":null},{"NOMBRE":"HUGO","LICENCIA":"17","DORSAL":"26","CODPARTICIPANTE":"39290299","FECHA_NACIMIENTO":2,"PORTERO":null},{"NOMBRE":"ANDERSON-IVAN","LICENCIA":"17","DORSAL":"34","CODPARTICIPANTE":"25802309","FECHA_NACIMIENTO":2,"PORTERO":null},{"NOMBRE":"SERGI","LICENCIA":"17","DORSAL":"36","CODPARTICIPANTE":"31146395","FECHA_NACIMIENTO":1,"PORTERO":null},{"NOMBRE":"FELIKS JAN","LICENCIA":"17","DORSAL":"41","CODPARTICIPANTE":"41780523","FECHA_NACIMIENTO":2,"PORTERO":null},{"NOMBRE":"XAVIER","LICENCIA":"17","DORSAL":"71","CODPARTICIPANTE":"28172082","FECHA_NACIMIENTO":1,"PORTERO":null},{"NOMBRE":"ALEX","LICENCIA":"17","DORSAL":"86","CODPARTICIPANTE":"39532261","FECHA_NACIMIENTO":2,"PORTERO":null}],"SUPLENTES":[{"NOMBRE":"GERARD","LICENCIA":"17","DORSAL":"6","CODPARTICIPANTE":"30169013","FECHA_NACIMIENTO":1,"PORTERO":null},{"NOMBRE":"ADRIAN","LICENCIA":"17","DORSAL":"7","CODPARTICIPANTE":"35934261","FECHA_NACIMIENTO":1,"PORTERO":null},{"NOMBRE":"BIEL","LICENCIA":"17","DORSAL":"13","CODPARTICIPANTE":"31568569","FECHA_NACIMIENTO":1,"PORTERO":1},{"NOMBRE":"DAVID","LICENCIA":"17","DORSAL":"17","CODPARTICIPANTE":"42369021","FECHA_NACIMIENTO":2,"PORTERO":null},{"NOMBRE":"ADRIA","LICENCIA":"17","DORSAL":"33","CODPARTICIPANTE":"45062580","FECHA_NACIMIENTO":2,"PORTERO":null},{"NOMBRE":"ARNAU","LICENCIA":"17","DORSAL":"35","CODPARTICIPANTE":"28624450","FECHA_NACIMIENTO":1,"PORTERO":null},{"NOMBRE":"FRANCISCO JAVIER","LICENCIA":"17","DORSAL":"42","CODPARTICIPANTE":"30045898","FECHA_NACIMIENTO":1,"PORTERO":null}],"COSTECNIC":{"Delegat":"KOBE BRYANT","Entrenador Titular":"DAVID"},"SUSTITUCIONES":[],"SANCIONES":[]}},"codacta":"3261945","titulars_local":[{"codparticipant":29609313,"codequip":18482665,"dorsal":1,"titularitats":0,"porter":1,"nom":"TONY","any":2011,"partits":1,"nom_equip":"FUNDACIÓ ESPORTIVA GRAMA B","colorequipacio1":"#0000FF","colorequipacio2":"#FF0000"},{"codparticipant":30529835,"codequip":18482665,"dorsal":4,"titularitats":1,"porter":null,"nom":"HUGO","any":2011,"partits":1,"nom_equip":"FUNDACIÓ ESPORTIVA GRAMA B","colorequipacio1":"#0000FF","colorequipacio2":"#FF0000"},{"codparticipant":28821553,"codequip":18482665,"dorsal":5,"titularitats":1,"porter":null,"nom":"ERIK","any":2010,"partits":1,"nom_equip":"FUNDACIÓ ESPORTIVA GRAMA B","colorequipacio1":"#0000FF","colorequipacio2":"#FF0000"},{"codparticipant":29681470,"codequip":18482665,"dorsal":6,"titularitats":1,"porter":null,"nom":"ALAN","any":2011,"partits":1,"nom_equip":"FUNDACIÓ ESPORTIVA GRAMA B","colorequipacio1":"#0000FF","colorequipacio2":"#FF0000"},{"codparticipant":35482879,"codequip":18482665,"dorsal":7,"titularitats":1,"porter":null,"nom":"EDGAR","any":2011,"partits":1,"nom_equip":"FUNDACIÓ ESPORTIVA GRAMA B","colorequipacio1":"#0000FF","colorequipacio2":"#FF0000"},{"codparticipant":33115773,"codequip":18482665,"dorsal":8,"titularitats":1,"porter":null,"nom":"CRISTIAN","any":2010,"partits":1,"nom_equip":"FUNDACIÓ ESPORTIVA GRAMA B","colorequipacio1":"#0000FF","colorequipacio2":"#FF0000"},{"codparticipant":35349740,"codequip":18482665,"dorsal":9,"titularitats":1,"porter":null,"nom":"GERARD","any":2011,"partits":1,"nom_equip":"FUNDACIÓ ESPORTIVA GRAMA B","colorequipacio1":"#0000FF","colorequipacio2":"#FF0000"},{"codparticipant":25851122,"codequip":18482665,"dorsal":10,"titularitats":0,"porter":null,"nom":"EDGAR","any":2010,"partits":1,"nom_equip":"FUNDACIÓ ESPORTIVA GRAMA B","colorequipacio1":"#0000FF","colorequipacio2":"#FF0000"},{"codparticipant":33306659,"codequip":18482665,"dorsal":11,"titularitats":1,"porter":null,"nom":"ALEIX","any":2011,"partits":1,"nom_equip":"FUNDACIÓ ESPORTIVA GRAMA B","colorequipacio1":"#0000FF","colorequipacio2":"#FF0000"},{"codparticipant":33656550,"codequip":18482665,"dorsal":12,"titularitats":1,"porter":null,"nom":"ALEX","any":2010,"partits":1,"nom_equip":"FUNDACIÓ ESPORTIVA GRAMA B","colorequipacio1":"#0000FF","colorequipacio2":"#FF0000"},{"codparticipant":28694367,"codequip":18482665,"dorsal":13,"titularitats":1,"porter":1,"nom":"SERGI","any":2011,"partits":1,"nom_equip":"FUNDACIÓ ESPORTIVA GRAMA B","colorequipacio1":"#0000FF","colorequipacio2":"#FF0000"},{"codparticipant":30992074,"codequip":18482665,"dorsal":14,"titularitats":0,"porter":null,"nom":"ERICK KAUAN","any":2011,"partits":1,"nom_equip":"FUNDACIÓ ESPORTIVA GRAMA B","colorequipacio1":"#0000FF","colorequipacio2":"#FF0000"},{"codparticipant":28505336,"codequip":18482665,"dorsal":15,"titularitats":1,"porter":null,"nom":"BIEL","any":2011,"partits":1,"nom_equip":"FUNDACIÓ ESPORTIVA GRAMA B","colorequipacio1":"#0000FF","colorequipacio2":"#FF0000"},{"codparticipant":28950517,"codequip":18482665,"dorsal":17,"titularitats":1,"porter":null,"nom":"POL","any":2011,"partits":1,"nom_equip":"FUNDACIÓ ESPORTIVA GRAMA B","colorequipacio1":"#0000FF","colorequipacio2":"#FF0000"},{"codparticipant":42176937,"codequip":18482665,"dorsal":19,"titularitats":0,"porter":null,"nom":"ALEX","any":2011,"partits":1,"nom_equip":"FUNDACIÓ ESPORTIVA GRAMA B","colorequipacio1":"#0000FF","colorequipacio2":"#FF0000"},{"codparticipant":27067769,"codequip":18482665,"dorsal":20,"titularitats":0,"porter":null,"nom":"ERIC","any":2011,"partits":1,"nom_equip":"FUNDACIÓ ESPORTIVA GRAMA B","colorequipacio1":"#0000FF","colorequipacio2":"#FF0000"}],"titulars_visitant":[{"codparticipant":26826506,"codequip":38099,"dorsal":1,"titularitats":1,"porter":1,"nom":"ADRIÀ","any":2010,"partits":1,"nom_equip":"MARTINENC, F.C. B","colorequipacio1":"#FF0000","colorequipacio2":null},{"codparticipant":30169013,"codequip":38099,"dorsal":6,"titularitats":0,"porter":null,"nom":"GERARD","any":2011,"partits":1,"nom_equip":"MARTINENC, F.C. B","colorequipacio1":"#FF0000","colorequipacio2":null},{"codparticipant":35934261,"codequip":38099,"dorsal":7,"titularitats":0,"porter":null,"nom":"ADRIAN","any":2011,"partits":1,"nom_equip":"MARTINENC, F.C. B","colorequipacio1":"#FF0000","colorequipacio2":null},{"codparticipant":28651862,"codequip":38099,"dorsal":10,"titularitats":1,"porter":null,"nom":"EDUARD","any":2011,"partits":1,"nom_equip":"MARTINENC, F.C. B","colorequipacio1":"#FF0000","colorequipacio2":null},{"codparticipant":31568569,"codequip":38099,"dorsal":13,"titularitats":0,"porter":1,"nom":"BIEL","any":2011,"partits":1,"nom_equip":"MARTINENC, F.C. B","colorequipacio1":"#FF0000","colorequipacio2":null},{"codparticipant":30169138,"codequip":38099,"dorsal":16,"titularitats":1,"porter":null,"nom":"GUIFRÉ","any":2011,"partits":1,"nom_equip":"MARTINENC, F.C. B","colorequipacio1":"#FF0000","colorequipacio2":null},{"codparticipant":42369021,"codequip":38099,"dorsal":17,"titularitats":0,"porter":null,"nom":"DAVID","any":2010,"partits":1,"nom_equip":"MARTINENC, F.C. B","colorequipacio1":"#FF0000","colorequipacio2":null},{"codparticipant":35030014,"codequip":38099,"dorsal":20,"titularitats":1,"porter":null,"nom":"ARNAU","any":2010,"partits":1,"nom_equip":"MARTINENC, F.C. B","colorequipacio1":"#FF0000","colorequipacio2":null},{"codparticipant":35212498,"codequip":38099,"dorsal":23,"titularitats":1,"porter":null,"nom":"AITOR","any":2011,"partits":1,"nom_equip":"MARTINENC, F.C. B","colorequipacio1":"#FF0000","colorequipacio2":null},{"codparticipant":39290299,"codequip":38099,"dorsal":26,"titularitats":1,"porter":null,"nom":"HUGO","any":2010,"partits":1,"nom_equip":"MARTINENC, F.C. B","colorequipacio1":"#FF0000","colorequipacio2":null},{"codparticipant":45062580,"codequip":38099,"dorsal":33,"titularitats":0,"porter":null,"nom":"ADRIA","any":2010,"partits":1,"nom_equip":"MARTINENC, F.C. B","colorequipacio1":"#FF0000","colorequipacio2":null},{"codparticipant":25802309,"codequip":38099,"dorsal":34,"titularitats":1,"porter":null,"nom":"ANDERSON-IVAN","any":2010,"partits":1,"nom_equip":"MARTINENC, F.C. B","colorequipacio1":"#FF0000","colorequipacio2":null},{"codparticipant":28624450,"codequip":38099,"dorsal":35,"titularitats":0,"porter":null,"nom":"ARNAU","any":2011,"partits":1,"nom_equip":"MARTINENC, F.C. B","colorequipacio1":"#FF0000","colorequipacio2":null},{"codparticipant":31146395,"codequip":38099,"dorsal":36,"titularitats":1,"porter":null,"nom":"SERGI","any":2011,"partits":1,"nom_equip":"MARTINENC, F.C. B","colorequipacio1":"#FF0000","colorequipacio2":null},{"codparticipant":41780523,"codequip":38099,"dorsal":41,"titularitats":1,"porter":null,"nom":"FELIKS JAN","any":2010,"partits":1,"nom_equip":"MARTINENC, F.C. B","colorequipacio1":"#FF0000","colorequipacio2":null},{"codparticipant":30045898,"codequip":38099,"dorsal":42,"titularitats":0,"porter":null,"nom":"FRANCISCO JAVIER","any":2011,"partits":1,"nom_equip":"MARTINENC, F.C. B","colorequipacio1":"#FF0000","colorequipacio2":null},{"codparticipant":28172082,"codequip":38099,"dorsal":71,"titularitats":1,"porter":null,"nom":"XAVIER","any":2011,"partits":1,"nom_equip":"MARTINENC, F.C. B","colorequipacio1":"#FF0000","colorequipacio2":null},{"codparticipant":39532261,"codequip":38099,"dorsal":86,"titularitats":1,"porter":null,"nom":"ALEX","any":2010,"partits":1,"nom_equip":"MARTINENC, F.C. B","colorequipacio1":"#FF0000","colorequipacio2":null}],"menuFollowTeams":[{"label":"Inf A","href":"/classificacio?id=48067560"},{"label":"Inf B","href":"/classificacio?id=48067652"},{"label":"Inf C","href":"/classificacio?id=48438234"},{"label":"Inf D","href":"/classificacio?id=48438025"}]}